[
    {
      "name": "Thomas Adamson",
      "message": "Restoran ini menyajikan hidangan lezat dengan bahan segar, suasana nyaman, dan pelayanan ramah, cocok untuk dinikmati bersama keluarga atau teman.",
      "avatar": "https://th.bing.com/th/id/OIP.O7Bt5RNeTpGluDAf1ysntwHaJQ?w=208&h=260&c=7&r=0&o=5&cb=iwc2&dpr=1.3&pid=1.7"
    },
    {
      "name": "Linda Parker",
      "message": "Pelayanan sangat cepat dan ramah. Saya sangat puas dengan produk yang diterima.",
      "avatar": "https://avatar.iran.liara.run/public/100"
    },
    {
      "name": "Ricky Fernando",
      "message": "Salah satu pengalaman belanja online terbaik! Kualitas top, pengiriman cepat.",
      "avatar": "https://avatar.iran.liara.run/public/94"
    },
    {
      "name": "Annisa Salsabila",
      "message": "Saya suka dengan desain kemasannya, dan rasanya juga enak banget!",
      "avatar": "https://avatar.iran.liara.run/public/73"
    },
    {
      "name": "Jamal Rachman",
      "message": "Sangat membantu, apalagi CS-nya cepat tanggap. Good job team!",
      "avatar": "https://avatar.iran.liara.run/public/56"
    }
  ]
  